Workbook

Sheet 0_Теория
A1: Занятие 8. Фильтрация, сортировка и вычисляемые столбцы
A3: Тема | B3: Как фильтровать строки, сортировать таблицу и создавать новые столбцы в Excel и Python.
A4: Зачем это нужно | B4: Фильтрация помогает быстро находить нужные строки, сортировка — видеть приоритеты, а новые столбцы — делать расчёты по данным.
A5: Ключевые методы Python | B5: pd.read_excel(), df[условие], &, sort_values(), df["new_column"] = ..., sum().
A6: Ключевые действия в Excel | B6: Автофильтр, IF+AND для проверки условий, сортировка по столбцу, формулы для расчёта revenue.
A7: Мини-проект урока | B7: Посчитать выручку по заказам, найти крупные заказы и отсортировать их по убыванию.

Sheet sales_data
A1: Лист sales_data — исходные данные для ноутбука
A2: order_id | B2: client | C2: city | D2: category | E2: product | F2: quantity | G2: price | H2: manager | I2: channel
A3: 1 | B3: Иванов И. | C3: Москва | D3: Электроника | E3: Смартфон | F3: 1 | G3: 30000 | H3: Анна С. | I3: Интернет-магазин
A4: 2 | B4: Петров П. | C4: Санкт-Петербург | D4: Бытовая техника | E4: Стиральная машина | F4: 2 | G4: 25010 | H4: Ольга К. | I4: Розница
A5: 3 | B5: Сидорова А. | C5: Екатеринбург | D5: Одежда | E5: Футболка | F5: 3 | G5: 1020 | H5: Сергей В. | I5: Опт
A6: 4 | B6: Кузнецова М. | C6: Новосибирск | D6: Книги | E6: Роман | F6: 4 | G6: 530 | H6: Дмитрий П. | I6: Интернет-магазин
A7: 5 | B7: Смирнов Д. | C7: Казань | D7: Спорттовары | E7: Тренажер | F7: 5 | G7: 8040 | H7: Екатерина Н. | I7: Розница
A8: 6 | B8: Попова Е. | C8: Нижний Новгород | D8: Электроника | E8: Планшет | F8: 6 | G8: 20050 | H8: Анна С. | I8: Опт
A9: 7 | B9: Васильев С. | C9: Челябинск | D9: Бытовая техника | E9: Холодильник | F9: 7 | G9: 35060 | H9: Ольга К. | I9: Интернет-магазин
A10: 8 | B10: Михайлова О. | C10: Омск | D10: Одежда | E10: Джинсы | F10: 8 | G10: 2070 | H10: Сергей В. | I10: Розница
A11: 9 | B11: Новиков А. | C11: Ростов-на-Дону | D11: Книги | E11: Энциклопедия | F11: 9 | G11: 1580 | H11: Дмитрий П. | I11: Опт
A12: 10 | B12: Федорова Н. | C12: Уфа | D12: Спорттовары | E12: Мяч | F12: 10 | G12: 1090 | H12: Екатерина Н. | I12: Интернет-магазин
A13: 11 | B13: Иванов И. | C13: Москва | D13: Электроника | E13: Ноутбук | F13: 1 | G13: 45100 | H13: Анна С. | I13: Розница
A14: 12 | B14: Петров П. | C14: Санкт-Петербург | D14: Бытовая техника | E14: Микроволновка | F14: 2 | G14: 8110 | H14: Ольга К. | I14: Опт
... A102: 100 | B102: Федорова Н. | C102: Уфа | D102: Спорттовары | E102: Мяч | F102: 10 | G102: 1990 | H102: Екатерина Н. | I102: Интернет-магазин

Sheet 1_Обзор
A1: Шаг 1. Загружаем таблицу и смотрим на её структуру
A3: Показатель | B3: Значение | D3: order_id | E3: client | F3: city | G3: category | H3: product | I3: quantity | J3: price | K3: manager | L3: channel
A4: Количество строк | B4: =COUNTA(sales_data!A3:A11) -> 9 | D4: =sales_data!A3 -> 1 | E4: =sales_data!B3 -> Иванов И. | F4: =sales_data!C3 -> Москва | G4: =sales_data!D3 -> Электроника | H4: =sales_data!E3 -> Смартфон | I4: =sales_data!F3 -> 1 | J4: =sales_data!G3 -> 30000 | K4: =sales_data!H3 -> Анна С. | L4: =sales_data!I3 -> Интернет-магазин
A5: Количество столбцов | B5: =COUNTA(sales_data!A2:I2) -> 9 | D5: =sales_data!A4 -> 2 | E5: =sales_data!B4 -> Петров П. | F5: =sales_data!C4 -> Санкт-Петербург | G5: =sales_data!D4 -> Бытовая техника | H5: =sales_data!E4 -> Стиральная машина | I5: =sales_data!F4 -> 2 | J5: =sales_data!G4 -> 25010 | K5: =sales_data!H4 -> Ольга К. | L5: =sales_data!I4 -> Розница
A6: Уникальных категорий | B6: =COUNTA(_xludf.UNIQUE(sales_data!D3:D11)) -> 1 | D6: =sales_data!A5 -> 3 | E6: =sales_data!B5 -> Сидорова А. | F6: =sales_data!C5 -> Екатеринбург | G6: =sales_data!D5 -> Одежда | H6: =sales_data!E5 -> Футболка | I6: =sales_data!F5 -> 3 | J6: =sales_data!G5 -> 1020 | K6: =sales_data!H5 -> Сергей В. | L6: =sales_data!I5 -> Опт
A7: Есть ли онлайн-заказы? | B7: =IF(COUNTIF(sales_data!I3:I11,"Онлайн")>0,"Да","Нет") -> Нет | D7: =sales_data!A6 -> 4 | E7: =sales_data!B6 -> Кузнецова М. | F7: =sales_data!C6 -> Новосибирск | G7: =sales_data!D6 -> Книги | H7: =sales_data!E6 -> Роман | I7: =sales_data!F6 -> 4 | J7: =sales_data!G6 -> 530 | K7: =sales_data!H6 -> Дмитрий П. | L7: =sales_data!I6 -> Интернет-магазин

Sheet 2_Фильтр_1
A1: Шаг 2. Фильтрация по одному условию: category == "Ноутбуки"
A3: order_id | B3: client | C3: city | D3: category | E3: product | F3: quantity | G3: price | H3: manager | I3: channel | J3: flag_ноутбуки | L3: Результат фильтра
A4: 201 | B4: ООО Альфа | C4: Москва | D4: Ноутбуки | E4: Notebook Air | F4: 2 | G4: 55000 | H4: Анна | I4: Онлайн | J4: =IF(D4="Ноутбуки","Да","Нет") -> Да | L4: order_id | M4: client | N4: city | O4: category | P4: product | Q4: quantity | R4: price | S4: manager | T4: channel
A5: 202 | B5: ООО Бета | C5: Санкт-Петербург | D5: Мониторы | E5: Monitor 27 | F5: 1 | G5: 23000 | H5: Борис | I5: Офлайн | J5: =IF(D5="Ноутбуки","Да","Нет") -> Нет | L5: =sales_data!A3 -> 1 | M5: =sales_data!B3 -> Иванов И. | N5: =sales_data!C3 -> Москва | O5: =sales_data!D3 -> Электроника | P5: =sales_data!E3 -> Смартфон | Q5: =sales_data!F3 -> 1 | R5: =sales_data!G3 -> 30000 | S5: =sales_data!H3 -> Анна С. | T5: =sales_data!I3 -> Интернет-магазин
A6: 203 | B6: ИП Гамма | C6: Москва | D6: Ноутбуки | E6: Notebook Pro | F6: 3 | G6: 72000 | H6: Анна | I6: Онлайн | J6: =IF(D6="Ноутбуки","Да","Нет") -> Да | L6: =sales_data!A5 -> 3 | M6: =sales_data!B5 -> Сидорова А. | N6: =sales_data!C5 -> Екатеринбург | O6: =sales_data!D5 -> Одежда | P6: =sales_data!E5 -> Футболка | Q6: =sales_data!F5 -> 3 | R6: =sales_data!G5 -> 1020 | S6: =sales_data!H5 -> Сергей В. | T6: =sales_data!I5 -> Опт
A7: 204 | B7: ООО Дельта | C7: Казань | D7: Периферия | E7: Mouse Pro | F7: 5 | G7: 2500 | H7: Виктор | I7: Маркетплейс | J7: =IF(D7="Ноутбуки","Да","Нет") -> Нет | L7: =sales_data!A8 -> 6 | M7: =sales_data!B8 -> Попова Е. | N7: =sales_data!C8 -> Нижний Новгород | O7: =sales_data!D8 -> Электроника | P7: =sales_data!E8 -> Планшет | Q7: =sales_data!F8 -> 6 | R7: =sales_data!G8 -> 20050 | S7: =sales_data!H8 -> Анна С. | T7: =sales_data!I8 -> Опт
A8: 205 | B8: ООО Эпсилон | C8: Москва | D8: Мониторы | E8: Monitor 24 | F8: 2 | G8: 18000 | H8: Анна | I8: Онлайн | J8: =IF(D8="Ноутбуки","Да","Нет") -> Нет | L8: =sales_data!A10 -> 8 | M8: =sales_data!B10 -> Михайлова О. | N8: =sales_data!C10 -> Омск | O8: =sales_data!D10 -> Одежда | P8: =sales_data!E10 -> Джинсы | Q8: =sales_data!F10 -> 8 | R8: =sales_data!G10 -> 2070 | S8: =sales_data!H10 -> Сергей В. | T8: =sales_data!I10 -> Розница
A9: 206 | B9: ИП Жасмин | C9: Екатеринбург | D9: Ноутбуки | E9: Notebook Lite | F9: 1 | G9: 49000 | H9: Борис | I9: Офлайн | J9: =IF(D9="Ноутбуки","Да","Нет") -> Да | L9: =sales_data!A11 -> 9 | M9: =sales_data!B11 -> Новиков А. | N9: =sales_data!C11 -> Ростов-на-Дону | O9: =sales_data!D11 -> Книги | P9: =sales_data!E11 -> Энциклопедия | Q9: =sales_data!F11 -> 9 | R9: =sales_data!G11 -> 1580 | S9: =sales_data!H11 -> Дмитрий П. | T9: =sales_data!I11 -> Опт
A10: 207 | B10: ООО Зета | C10: Москва | D10: Периферия | E10: Keyboard X | F10: 4 | G10: 4000 | H10: Виктор | I10: Онлайн | J10: =IF(D10="Ноутбуки","Да","Нет") -> Нет
A11: 208 | B11: ООО Ита | C11: Новосибирск | D11: Ноутбуки | E11: Notebook Air | F11: 2 | G11: 55000 | H11: Анна | I11: Маркетплейс | J11: =IF(D11="Ноутбуки","Да","Нет") -> Да | L11: Количество строк после фильтра | M11: =COUNTIF(J4:J12,"Да") -> 5
A12: 209 | B12: ООО Каппа | C12: Москва | D12: Ноутбуки | E12: Notebook Start | F12: 1 | G12: 43000 | H12: Борис | I12: Офлайн | J12: =IF(D12="Ноутбуки","Да","Нет") -> Да

Sheet 3_Фильтр_2
A1: Шаг 3. Фильтрация по двум условиям: city == "Москва" и channel == "Онлайн"
A3: order_id | B3: client | C3: city | D3: category | E3: product | F3: quantity | G3: price | H3: manager | I3: channel | J3: flag_москва_онлайн | L3: Результат фильтра
A4: 201 | B4: ООО Альфа | C4: Москва | D4: Ноутбуки | E4: Notebook Air | F4: 2 | G4: 55000 | H4: Анна | I4: Онлайн | J4: =IF(AND(C4="Москва",I4="Онлайн"),"Да","Нет") -> Да | L4: order_id | M4: client | N4: city | O4: category | P4: product | Q4: quantity | R4: price | S4: manager | T4: channel
A5: 202 | B5: ООО Бета | C5: Санкт-Петербург | D5: Мониторы | E5: Monitor 27 | F5: 1 | G5: 23000 | H5: Борис | I5: Офлайн | J5: =IF(AND(C5="Москва",I5="Онлайн"),"Да","Нет") -> Нет | L5: =sales_data!A3 -> 1 | M5: =sales_data!B3 -> Иванов И. | N5: =sales_data!C3 -> Москва | O5: =sales_data!D3 -> Электроника | P5: =sales_data!E3 -> Смартфон | Q5: =sales_data!F3 -> 1 | R5: =sales_data!G3 -> 30000 | S5: =sales_data!H3 -> Анна С. | T5: =sales_data!I3 -> Интернет-магазин
A6: 203 | B6: ИП Гамма | C6: Москва | D6: Ноутбуки | E6: Notebook Pro | F6: 3 | G6: 72000 | H6: Анна | I6: Онлайн | J6: =IF(AND(C6="Москва",I6="Онлайн"),"Да","Нет") -> Да | L6: =sales_data!A5 -> 3 | M6: =sales_data!B5 -> Сидорова А. | N6: =sales_data!C5 -> Екатеринбург | O6: =sales_data!D5 -> Одежда | P6: =sales_data!E5 -> Футболка | Q6: =sales_data!F5 -> 3 | R6: =sales_data!G5 -> 1020 | S6: =sales_data!H5 -> Сергей В. | T6: =sales_data!I5 -> Опт
A7: 204 | B7: ООО Дельта | C7: Казань | D7: Периферия | E7: Mouse Pro | F7: 5 | G7: 2500 | H7: Виктор | I7: Маркетплейс | J7: =IF(AND(C7="Москва",I7="Онлайн"),"Да","Нет") -> Нет | L7: =sales_data!A7 -> 5 | M7: =sales_data!B7 -> Смирнов Д. | N7: =sales_data!C7 -> Казань | O7: =sales_data!D7 -> Спорттовары | P7: =sales_data!E7 -> Тренажер | Q7: =sales_data!F7 -> 5 | R7: =sales_data!G7 -> 8040 | S7: =sales_data!H7 -> Екатерина Н. | T7: =sales_data!I7 -> Розница
A8: 205 | B8: ООО Эпсилон | C8: Москва | D8: Мониторы | E8: Monitor 24 | F8: 2 | G8: 18000 | H8: Анна | I8: Онлайн | J8: =IF(AND(C8="Москва",I8="Онлайн"),"Да","Нет") -> Да | L8: =sales_data!A9 -> 7 | M8: =sales_data!B9 -> Васильев С. | N8: =sales_data!C9 -> Челябинск | O8: =sales_data!D9 -> Бытовая техника | P8: =sales_data!E9 -> Холодильник | Q8: =sales_data!F9 -> 7 | R8: =sales_data!G9 -> 35060 | S8: =sales_data!H9 -> Ольга К. | T8: =sales_data!I9 -> Интернет-магазин
A9: 206 | B9: ИП Жасмин | C9: Екатеринбург | D9: Ноутбуки | E9: Notebook Lite | F9: 1 | G9: 49000 | H9: Борис | I9: Офлайн | J9: =IF(AND(C9="Москва",I9="Онлайн"),"Да","Нет") -> Нет
A10: 207 | B10: ООО Зета | C10: Москва | D10: Периферия | E10: Keyboard X | F10: 4 | G10: 4000 | H10: Виктор | I10: Онлайн | J10: =IF(AND(C10="Москва",I10="Онлайн"),"Да","Нет") -> Да | L10: Количество строк после фильтра | M10: =COUNTIF(J4:J12,"Да") -> 4
A11: 208 | B11: ООО Ита | C11: Новосибирск | D11: Ноутбуки | E11: Notebook Air | F11: 2 | G11: 55000 | H11: Анна | I11: Маркетплейс | J11: =IF(AND(C11="Москва",I11="Онлайн"),"Да","Нет") -> Нет
A12: 209 | B12: ООО Каппа | C12: Москва | D12: Ноутбуки | E12: Notebook Start | F12: 1 | G12: 43000 | H12: Борис | I12: Офлайн | J12: =IF(AND(C12="Москва",I12="Онлайн"),"Да","Нет") -> Нет

Sheet 4_Сортировка
A1: Шаг 4. Сортировка по price по убыванию
A3: order_id | B3: client | C3: city | D3: category | E3: product | F3: quantity | G3: price | H3: manager | I3: channel | J3: price_rank | L3: Отсортированная таблица
A4: 201 | B4: ООО Альфа | C4: Москва | D4: Ноутбуки | E4: Notebook Air | F4: 2 | G4: 55000 | H4: Анна | I4: Онлайн | J4: =RANK(G4,$G$4:$G$12,0)+COUNTIF($G$4:G4,G4)-1 -> 2 | L4: order_id | M4: client | N4: city | O4: category | P4: product | Q4: quantity | R4: price | S4: manager | T4: channel
A5: 202 | B5: ООО Бета | C5: Санкт-Петербург | D5: Мониторы | E5: Monitor 27 | F5: 1 | G5: 23000 | H5: Борис | I5: Офлайн | J5: =RANK(G5,$G$4:$G$12,0)+COUNTIF($G$4:G5,G5)-1 -> 6 | L5: =sales_data!A5 -> 3 | M5: =sales_data!B5 -> Сидорова А. | N5: =sales_data!C5 -> Екатеринбург | O5: =sales_data!D5 -> Одежда | P5: =sales_data!E5 -> Футболка | Q5: =sales_data!F5 -> 3 | R5: =sales_data!G5 -> 1020 | S5: =sales_data!H5 -> Сергей В. | T5: =sales_data!I5 -> Опт
A6: 203 | B6: ИП Гамма | C6: Москва | D6: Ноутбуки | E6: Notebook Pro | F6: 3 | G6: 72000 | H6: Анна | I6: Онлайн | J6: =RANK(G6,$G$4:$G$12,0)+COUNTIF($G$4:G6,G6)-1 -> 1 | L6: =sales_data!A3 -> 1 | M6: =sales_data!B3 -> Иванов И. | N6: =sales_data!C3 -> Москва | O6: =sales_data!D3 -> Электроника | P6: =sales_data!E3 -> Смартфон | Q6: =sales_data!F3 -> 1 | R6: =sales_data!G3 -> 30000 | S6: =sales_data!H3 -> Анна С. | T6: =sales_data!I3 -> Интернет-магазин
A7: 204 | B7: ООО Дельта | C7: Казань | D7: Периферия | E7: Mouse Pro | F7: 5 | G7: 2500 | H7: Виктор | I7: Маркетплейс | J7: =RANK(G7,$G$4:$G$12,0)+COUNTIF($G$4:G7,G7)-1 -> 9 | L7: =sales_data!A10 -> 8 | M7: =sales_data!B10 -> Михайлова О. | N7: =sales_data!C10 -> Омск | O7: =sales_data!D10 -> Одежда | P7: =sales_data!E10 -> Джинсы | Q7: =sales_data!F10 -> 8 | R7: =sales_data!G10 -> 2070 | S7: =sales_data!H10 -> Сергей В. | T7: =sales_data!I10 -> Розница
A8: 205 | B8: ООО Эпсилон | C8: Москва | D8: Мониторы | E8: Monitor 24 | F8: 2 | G8: 18000 | H8: Анна | I8: Онлайн | J8: =RANK(G8,$G$4:$G$12,0)+COUNTIF($G$4:G8,G8)-1 -> 7 | L8: =sales_data!A8 -> 6 | M8: =sales_data!B8 -> Попова Е. | N8: =sales_data!C8 -> Нижний Новгород | O8: =sales_data!D8 -> Электроника | P8: =sales_data!E8 -> Планшет | Q8: =sales_data!F8 -> 6 | R8: =sales_data!G8 -> 20050 | S8: =sales_data!H8 -> Анна С. | T8: =sales_data!I8 -> Опт
A9: 206 | B9: ИП Жасмин | C9: Екатеринбург | D9: Ноутбуки | E9: Notebook Lite | F9: 1 | G9: 49000 | H9: Борис | I9: Офлайн | J9: =RANK(G9,$G$4:$G$12,0)+COUNTIF($G$4:G9,G9)-1 -> 4 | L9: =sales_data!A11 -> 9 | M9: =sales_data!B11 -> Новиков А. | N9: =sales_data!C11 -> Ростов-на-Дону | O9: =sales_data!D11 -> Книги | P9: =sales_data!E11 -> Энциклопедия | Q9: =sales_data!F11 -> 9 | R9: =sales_data!G11 -> 1580 | S9: =sales_data!H11 -> Дмитрий П. | T9: =sales_data!I11 -> Опт
A10: 207 | B10: ООО Зета | C10: Москва | D10: Периферия | E10: Keyboard X | F10: 4 | G10: 4000 | H10: Виктор | I10: Онлайн | J10: =RANK(G10,$G$4:$G$12,0)+COUNTIF($G$4:G10,G10)-1 -> 8 | L10: =sales_data!A4 -> 2 | M10: =sales_data!B4 -> Петров П. | N10: =sales_data!C4 -> Санкт-Петербург | O10: =sales_data!D4 -> Бытовая техника | P10: =sales_data!E4 -> Стиральная машина | Q10: =sales_data!F4 -> 2 | R10: =sales_data!G4 -> 25010 | S10: =sales_data!H4 -> Ольга К. | T10: =sales_data!I4 -> Розница
A11: 208 | B11: ООО Ита | C11: Новосибирск | D11: Ноутбуки | E11: Notebook Air | F11: 2 | G11: 55000 | H11: Анна | I11: Маркетплейс | J11: =RANK(G11,$G$4:$G$12,0)+COUNTIF($G$4:G11,G11)-1 -> 3 | L11: =sales_data!A7 -> 5 | M11: =sales_data!B7 -> Смирнов Д. | N11: =sales_data!C7 -> Казань | O11: =sales_data!D7 -> Спорттовары | P11: =sales_data!E7 -> Тренажер | Q11: =sales_data!F7 -> 5 | R11: =sales_data!G7 -> 8040 | S11: =sales_data!H7 -> Екатерина Н. | T11: =sales_data!I7 -> Розница
A12: 209 | B12: ООО Каппа | C12: Москва | D12: Ноутбуки | E12: Notebook Start | F12: 1 | G12: 43000 | H12: Борис | I12: Офлайн | J12: =RANK(G12,$G$4:$G$12,0)+COUNTIF($G$4:G12,G12)-1 -> 5 | L12: =sales_data!A9 -> 7 | M12: =sales_data!B9 -> Васильев С. | N12: =sales_data!C9 -> Челябинск | O12: =sales_data!D9 -> Бытовая техника | P12: =sales_data!E9 -> Холодильник | Q12: =sales_data!F9 -> 7 | R12: =sales_data!G9 -> 35060 | S12: =sales_data!H9 -> Ольга К. | T12: =sales_data!I9 -> Интернет-магазин
L13: =sales_data!A6 -> 4 | M13: =sales_data!B6 -> Кузнецова М. | N13: =sales_data!C6 -> Новосибирск | O13: =sales_data!D6 -> Книги | P13: =sales_data!E6 -> Роман | Q13: =sales_data!F6 -> 4 | R13: =sales_data!G6 -> 530 | S13: =sales_data!H6 -> Дмитрий П. | T13: =sales_data!I6 -> Интернет-магазин
L15: Самый дорогой заказ | M15: =L5 -> 3

Sheet 5_Новые_столбцы
A1: Шаг 5. Создаём столбец revenue и ищем крупные заказы
A3: order_id | B3: client | C3: city | D3: category | E3: product | F3: quantity | G3: price | H3: manager | I3: channel | J3: revenue | K3: big_order | M3: Мини-задача: заказы с revenue >= 100000
A4: 201 | B4: ООО Альфа | C4: Москва | D4: Ноутбуки | E4: Notebook Air | F4: 2 | G4: 55000 | H4: Анна | I4: Онлайн | J4: =F4*G4 -> 110000 | K4: =IF(J4>=100000,"Крупный заказ","Обычный") -> Крупный заказ | M4: order_id | N4: client | O4: city | P4: category | Q4: product | R4: quantity | S4: price | T4: manager | U4: channel | V4: revenue
A5: 202 | B5: ООО Бета | C5: Санкт-Петербург | D5: Мониторы | E5: Monitor 27 | F5: 1 | G5: 23000 | H5: Борис | I5: Офлайн | J5: =F5*G5 -> 23000 | K5: =IF(J5>=100000,"Крупный заказ","Обычный") -> Обычный | M5: =sales_data!A5 -> 3 | N5: =sales_data!B5 -> Сидорова А. | O5: =sales_data!C5 -> Екатеринбург | P5: =sales_data!D5 -> Одежда | Q5: =sales_data!E5 -> Футболка | R5: =sales_data!F5 -> 3 | S5: =sales_data!G5 -> 1020 | T5: =sales_data!H5 -> Сергей В. | U5: =sales_data!I5 -> Опт | V5: =R5*S5 -> 3060
A6: 203 | B6: ИП Гамма | C6: Москва | D6: Ноутбуки | E6: Notebook Pro | F6: 3 | G6: 72000 | H6: Анна | I6: Онлайн | J6: =F6*G6 -> 216000 | K6: =IF(J6>=100000,"Крупный заказ","Обычный") -> Крупный заказ | M6: =sales_data!A3 -> 1 | N6: =sales_data!B3 -> Иванов И. | O6: =sales_data!C3 -> Москва | P6: =sales_data!D3 -> Электроника | Q6: =sales_data!E3 -> Смартфон | R6: =sales_data!F3 -> 1 | S6: =sales_data!G3 -> 30000 | T6: =sales_data!H3 -> Анна С. | U6: =sales_data!I3 -> Интернет-магазин | V6: =R6*S6 -> 30000
A7: 204 | B7: ООО Дельта | C7: Казань | D7: Периферия | E7: Mouse Pro | F7: 5 | G7: 2500 | H7: Виктор | I7: Маркетплейс | J7: =F7*G7 -> 12500 | K7: =IF(J7>=100000,"Крупный заказ","Обычный") -> Обычный | M7: =sales_data!A10 -> 8 | N7: =sales_data!B10 -> Михайлова О. | O7: =sales_data!C10 -> Омск | P7: =sales_data!D10 -> Одежда | Q7: =sales_data!E10 -> Джинсы | R7: =sales_data!F10 -> 8 | S7: =sales_data!G10 -> 2070 | T7: =sales_data!H10 -> Сергей В. | U7: =sales_data!I10 -> Розница | V7: =R7*S7 -> 16560
A8: 205 | B8: ООО Эпсилон | C8: Москва | D8: Мониторы | E8: Monitor 24 | F8: 2 | G8: 18000 | H8: Анна | I8: Онлайн | J8: =F8*G8 -> 36000 | K8: =IF(J8>=100000,"Крупный заказ","Обычный") -> Обычный
A9: 206 | B9: ИП Жасмин | C9: Екатеринбург | D9: Ноутбуки | E9: Notebook Lite | F9: 1 | G9: 49000 | H9: Борис | I9: Офлайн | J9: =F9*G9 -> 49000 | K9: =IF(J9>=100000,"Крупный заказ","Обычный") -> Обычный
A10: 207 | B10: ООО Зета | C10: Москва | D10: Периферия | E10: Keyboard X | F10: 4 | G10: 4000 | H10: Виктор | I10: Онлайн | J10: =F10*G10 -> 16000 | K10: =IF(J10>=100000,"Крупный заказ","Обычный") -> Обычный | M10: Общая выручка | N10: =SUM(J4:J12) -> 615500
A11: 208 | B11: ООО Ита | C11: Новосибирск | D11: Ноутбуки | E11: Notebook Air | F11: 2 | G11: 55000 | H11: Анна | I11: Маркетплейс | J11: =F11*G11 -> 110000 | K11: =IF(J11>=100000,"Крупный заказ","Обычный") -> Крупный заказ | M11: Количество крупных заказов | N11: =COUNTIF(K4:K12,"Крупный заказ") -> 3
A12: 209 | B12: ООО Каппа | C12: Москва | D12: Ноутбуки | E12: Notebook Start | F12: 1 | G12: 43000 | H12: Борис | I12: Офлайн | J12: =F12*G12 -> 43000 | K12: =IF(J12>=100000,"Крупный заказ","Обычный") -> Обычный

Sheet 6_Тест
A1: Тест по занятию 8
A3: Вопрос | B3: Правильный ответ | C3: Подсказка
A4: Сколько строк в исходной таблице? | B4: =COUNTA(sales_data!A3:A11) -> 9 | C4: Аналог df.shape[0]
A5: Сколько заказов попадает в фильтр category == "Ноутбуки"? | B5: =COUNTIF('2_Фильтр_1'!J4:J12,"Да") -> 5 | C5: Смотрите sheet 2 или notebook cell 2
A6: Сколько заказов попадает в фильтр city == "Москва" и channel == "Онлайн"? | B6: =COUNTIF('3_Фильтр_2'!J4:J12,"Да") -> 4 | C6: Используйте AND в Excel и & в pandas
A7: Какая общая выручка после создания столбца revenue? | B7: =SUM('5_Новые_столбцы'!J4:J12) -> 615500 | C7: Это сумма quantity * price
A8: Сколько крупных заказов с revenue >= 100000? | B8: =COUNTIF('5_Новые_столбцы'!K4:K12,"Крупный заказ") -> 3 | C8: Смотрите столбец big_order
