Workbook

Sheet 0_Теория
A1: Занятие 9. Группировка, агрегаты и мини-сводные таблицы
A3: Тема | B3: Как считать агрегаты, группировать данные по менеджерам и категориям, а также строить мини-сводные таблицы в Excel и Python.
A4: Зачем это нужно | B4: Группировка помогает быстро увидеть общую выручку, количество заказов и лидеров продаж без просмотра каждой строки вручную.
A5: Ключевые методы Python | B5: groupby(), agg(), reset_index(), sort_values(), pivot_table().
A6: Ключевые действия в Excel | B6: SUM, AVERAGE, COUNTA, SUMIFS, COUNTIFS, INDEX/MATCH, мини-сводная таблица по строкам и столбцам.
A7: Мини-проект урока | B7: Определить лидера по выручке среди менеджеров и сравнить категории товаров по выручке.

Sheet sales_data
A1: Лист sales_data — исходные данные для ноутбука
A2: order_id | B2: month | C2: manager | D2: city | E2: category | F2: product | G2: quantity | H2: price | I2: revenue
A3: 1 | B3: Январь | C3: Иванов А.С. | D3: Москва | E3: Офисная мебель | F3: Кресло | G3: 8 | H3: 21360.92 | I3: =G3*H3 -> 170887.36
A4: 2 | B4: Февраль | C4: Смирнова О.В. | D4: Москва | E4: Расходные материалы | F4: Кабель HDMI | G4: 2 | H4: 4954.68 | I4: =G4*H4 -> 9909.36
A5: 3 | B5: Март | C5: Петров В.Д. | D5: Казань | E5: Расходные материалы | F5: Картридж | G5: 18 | H5: 30226.23 | I5: =G5*H5 -> 544072.14
A6: 4 | B6: Апрель | C6: Смирнова О.В. | D6: Екатеринбург | E6: Бытовая техника | F6: Пылесос | G6: 19 | H6: 42089.51 | I6: =G6*H6 -> 799700.69
A7: 5 | B7: Май | C7: Петров В.Д. | D7: Екатеринбург | E7: Офисная мебель | F7: Шкаф | G7: 5 | H7: 32689.41 | I7: =G7*H7 -> 163447.05
A8: 6 | B8: Июнь | C8: Иванов А.С. | D8: Москва | E8: Канцелярия | F8: Бумага А4 | G8: 12 | H8: 127200.41 | I8: =G8*H8 -> 1526404.9
A9: 7 | B9: Июль | C9: Сидорова Е.К. | D9: Москва | E9: Канцелярия | F9: Ежедневник | G9: 4 | H9: 145980.81 | I9: =G9*H9 -> 583923.24
A10: 8 | B10: Август | C10: Иванов А.С. | D10: Казань | E10: Офисная мебель | F10: Тумба | G10: 12 | H10: 86814.15 | I10: =G10*H10 -> 1041769.8
A11: 9 | B11: Сентябрь | C11: Иванов А.С. | D11: Москва | E11: Бытовая техника | F11: Микроволновка | G11: 3 | H11: 128370 | I11: =G11*H11 -> 385110
A12: 10 | B12: Октябрь | C12: Кузнецов М.Р. | D12: Новосибирск | E12: Канцелярия | F12: Папка | G12: 6 | H12: 55842.05 | I12: =G12*H12 -> 335052.3
A13: 11 | B13: Ноябрь | C13: Сидорова Е.К. | D13: Москва | E13: Расходные материалы | F13: Тонер | G13: 18 | H13: 109504.46 | I13: =G13*H13 -> 1971080.3
A14: 12 | B14: Декабрь | C14: Кузнецов М.Р. | D14: Екатеринбург | E14: Офисная мебель | F14: Тумба | G14: 8 | H14: 102849.83 | I14: =G14*H14 -> 822798.64
... A102: 100 | B102: Апрель | C102: Сидорова Е.К. | D102: Новосибирск | E102: Бытовая техника | F102: Холодильник | G102: 9 | H102: 132303.86 | I102: =G102*H102 -> 1190734.7
I103: =SUM(I3:I102) -> 65146246 | J103: =MIN(I3:I102) -> 7408.95 | K103: =MAX(I3:I102) -> 2952865.2

Sheet 1_Агрегаты
A1: Шаг 1. Считаем базовые агрегаты по таблице
A3: Показатель | B3: Формула в Excel | C3: Значение | D3: Комментарий | F3: Первые строки исходной таблицы
A4: Количество заказов | B4: =COUNTA(sales_data!A3:A14) -> 12 | C4: =COUNTA(sales_data!A3:A14) -> 12 | D4: Аналог df.shape[0] или count по order_id. | F4: order_id | G4: month | H4: manager | I4: city | J4: category | K4: product | L4: quantity | M4: price | N4: revenue
A5: Общая выручка | B5: =SUM(sales_data!I3:I14) -> 8354155.8 | C5: =SUM(sales_data!I3:I14) -> 8354155.8 | D5: Аналог df['revenue'].sum(). | F5: =sales_data!A3 -> 1 | G5: =sales_data!B3 -> Январь | H5: =sales_data!C3 -> Иванов А.С. | I5: =sales_data!D3 -> Москва | J5: =sales_data!E3 -> Офисная мебель | K5: =sales_data!F3 -> Кресло | L5: =sales_data!G3 -> 8 | M5: =sales_data!H3 -> 21360.92 | N5: =sales_data!I3 -> 170887.36
A6: Средняя выручка заказа | B6: =AVERAGE(sales_data!I3:I14) -> 696179.65 | C6: =AVERAGE(sales_data!I3:I14) -> 696179.65 | D6: Аналог df['revenue'].mean(). | F6: =sales_data!A4 -> 2 | G6: =sales_data!B4 -> Февраль | H6: =sales_data!C4 -> Смирнова О.В. | I6: =sales_data!D4 -> Москва | J6: =sales_data!E4 -> Расходные материалы | K6: =sales_data!F4 -> Кабель HDMI | L6: =sales_data!G4 -> 2 | M6: =sales_data!H4 -> 4954.68 | N6: =sales_data!I4 -> 9909.36
A7: Максимальная выручка заказа | B7: =MAX(sales_data!I3:I14) -> 1971080.3 | C7: =MAX(sales_data!I3:I14) -> 1971080.3 | D7: Аналог df['revenue'].max(). | F7: =sales_data!A5 -> 3 | G7: =sales_data!B5 -> Март | H7: =sales_data!C5 -> Петров В.Д. | I7: =sales_data!D5 -> Казань | J7: =sales_data!E5 -> Расходные материалы | K7: =sales_data!F5 -> Картридж | L7: =sales_data!G5 -> 18 | M7: =sales_data!H5 -> 30226.23 | N7: =sales_data!I5 -> 544072.14
A8: Минимальная выручка заказа | B8: =MIN(sales_data!I3:I14) -> 9909.36 | C8: =MIN(sales_data!I3:I14) -> 9909.36 | D8: Аналог df['revenue'].min(). | F8: =sales_data!A6 -> 4 | G8: =sales_data!B6 -> Апрель | H8: =sales_data!C6 -> Смирнова О.В. | I8: =sales_data!D6 -> Екатеринбург | J8: =sales_data!E6 -> Бытовая техника | K8: =sales_data!F6 -> Пылесос | L8: =sales_data!G6 -> 19 | M8: =sales_data!H6 -> 42089.51 | N8: =sales_data!I6 -> 799700.69
F9: =sales_data!A7 -> 5 | G9: =sales_data!B7 -> Май | H9: =sales_data!C7 -> Петров В.Д. | I9: =sales_data!D7 -> Екатеринбург | J9: =sales_data!E7 -> Офисная мебель | K9: =sales_data!F7 -> Шкаф | L9: =sales_data!G7 -> 5 | M9: =sales_data!H7 -> 32689.41 | N9: =sales_data!I7 -> 163447.05

Sheet 2_Группировка_1
A1: Шаг 2. Группировка по manager
A3: manager | B3: total_revenue | C3: orders | D3: total_quantity | E3: avg_revenue | G3: Исходные поля для сравнения
A4: Анна | B4: =SUMIFS(sales_data!$I$3:$I$14,sales_data!$C$3:$C$14,$A4) -> 0 | C4: =COUNTIF(sales_data!$C$3:$C$14,$A4) -> 0 | D4: =SUMIFS(sales_data!$G$3:$G$14,sales_data!$C$3:$C$14,$A4) -> 0 | E4: =B4/C4 -> #DIV/0! | G4: month | H4: manager | I4: category | J4: revenue
A5: Борис | B5: =SUMIFS(sales_data!$I$3:$I$14,sales_data!$C$3:$C$14,$A5) -> 0 | C5: =COUNTIF(sales_data!$C$3:$C$14,$A5) -> 0 | D5: =SUMIFS(sales_data!$G$3:$G$14,sales_data!$C$3:$C$14,$A5) -> 0 | E5: =B5/C5 -> #DIV/0! | G5: =sales_data!B3 -> Январь | H5: =sales_data!C3 -> Иванов А.С. | I5: =sales_data!E3 -> Офисная мебель | J5: =sales_data!I3 -> 170887.36
A6: Светлана | B6: =SUMIFS(sales_data!$I$3:$I$14,sales_data!$C$3:$C$14,$A6) -> 0 | C6: =COUNTIF(sales_data!$C$3:$C$14,$A6) -> 0 | D6: =SUMIFS(sales_data!$G$3:$G$14,sales_data!$C$3:$C$14,$A6) -> 0 | E6: =B6/C6 -> #DIV/0! | G6: =sales_data!B4 -> Февраль | H6: =sales_data!C4 -> Смирнова О.В. | I6: =sales_data!E4 -> Расходные материалы | J6: =sales_data!I4 -> 9909.36
G7: =sales_data!B5 -> Март | H7: =sales_data!C5 -> Петров В.Д. | I7: =sales_data!E5 -> Расходные материалы | J7: =sales_data!I5 -> 544072.14
G8: =sales_data!B6 -> Апрель | H8: =sales_data!C6 -> Смирнова О.В. | I8: =sales_data!E6 -> Бытовая техника | J8: =sales_data!I6 -> 799700.69
G9: =sales_data!B7 -> Май | H9: =sales_data!C7 -> Петров В.Д. | I9: =sales_data!E7 -> Офисная мебель | J9: =sales_data!I7 -> 163447.05
G10: =sales_data!B8 -> Июнь | H10: =sales_data!C8 -> Иванов А.С. | I10: =sales_data!E8 -> Канцелярия | J10: =sales_data!I8 -> 1526404.9

Sheet 3_Группировка_2
A1: Шаг 3. Группировка по month и category
A3: month | B3: category | C3: total_revenue | D3: total_quantity | E3: orders | G3: Мини-сводная: revenue по месяцам и категориям
A4: Январь | B4: Ноутбуки | C4: =SUMIFS(sales_data!$I$3:$I$14,sales_data!$B$3:$B$14,$A4,sales_data!$E$3:$E$14,$B4) -> 0 | D4: =SUMIFS(sales_data!$G$3:$G$14,sales_data!$B$3:$B$14,$A4,sales_data!$E$3:$E$14,$B4) -> 0 | E4: =COUNTIFS(sales_data!$B$3:$B$14,$A4,sales_data!$E$3:$E$14,$B4) -> 0 | H4: Ноутбуки | I4: Мониторы | J4: Периферия | K4: Принтеры
A5: Январь | B5: Мониторы | C5: =SUMIFS(sales_data!$I$3:$I$14,sales_data!$B$3:$B$14,$A5,sales_data!$E$3:$E$14,$B5) -> 0 | D5: =SUMIFS(sales_data!$G$3:$G$14,sales_data!$B$3:$B$14,$A5,sales_data!$E$3:$E$14,$B5) -> 0 | E5: =COUNTIFS(sales_data!$B$3:$B$14,$A5,sales_data!$E$3:$E$14,$B5) -> 0 | G5: Январь | H5: =SUMIFS(sales_data!$I$3:$I$14,sales_data!$B$3:$B$14,$G5,sales_data!$E$3:$E$14,H$4) -> 0 | I5: =SUMIFS(sales_data!$I$3:$I$14,sales_data!$B$3:$B$14,$G5,sales_data!$E$3:$E$14,I$4) -> 0 | J5: =SUMIFS(sales_data!$I$3:$I$14,sales_data!$B$3:$B$14,$G5,sales_data!$E$3:$E$14,J$4) -> 0 | K5: =SUMIFS(sales_data!$I$3:$I$14,sales_data!$B$3:$B$14,$G5,sales_data!$E$3:$E$14,K$4) -> 0
A6: Февраль | B6: Мониторы | C6: =SUMIFS(sales_data!$I$3:$I$14,sales_data!$B$3:$B$14,$A6,sales_data!$E$3:$E$14,$B6) -> 0 | D6: =SUMIFS(sales_data!$G$3:$G$14,sales_data!$B$3:$B$14,$A6,sales_data!$E$3:$E$14,$B6) -> 0 | E6: =COUNTIFS(sales_data!$B$3:$B$14,$A6,sales_data!$E$3:$E$14,$B6) -> 0 | G6: Февраль | H6: =SUMIFS(sales_data!$I$3:$I$14,sales_data!$B$3:$B$14,$G6,sales_data!$E$3:$E$14,H$4) -> 0 | I6: =SUMIFS(sales_data!$I$3:$I$14,sales_data!$B$3:$B$14,$G6,sales_data!$E$3:$E$14,I$4) -> 0 | J6: =SUMIFS(sales_data!$I$3:$I$14,sales_data!$B$3:$B$14,$G6,sales_data!$E$3:$E$14,J$4) -> 0 | K6: =SUMIFS(sales_data!$I$3:$I$14,sales_data!$B$3:$B$14,$G6,sales_data!$E$3:$E$14,K$4) -> 0
A7: Февраль | B7: Ноутбуки | C7: =SUMIFS(sales_data!$I$3:$I$14,sales_data!$B$3:$B$14,$A7,sales_data!$E$3:$E$14,$B7) -> 0 | D7: =SUMIFS(sales_data!$G$3:$G$14,sales_data!$B$3:$B$14,$A7,sales_data!$E$3:$E$14,$B7) -> 0 | E7: =COUNTIFS(sales_data!$B$3:$B$14,$A7,sales_data!$E$3:$E$14,$B7) -> 0 | G7: Март | H7: =SUMIFS(sales_data!$I$3:$I$14,sales_data!$B$3:$B$14,$G7,sales_data!$E$3:$E$14,H$4) -> 0 | I7: =SUMIFS(sales_data!$I$3:$I$14,sales_data!$B$3:$B$14,$G7,sales_data!$E$3:$E$14,I$4) -> 0 | J7: =SUMIFS(sales_data!$I$3:$I$14,sales_data!$B$3:$B$14,$G7,sales_data!$E$3:$E$14,J$4) -> 0 | K7: =SUMIFS(sales_data!$I$3:$I$14,sales_data!$B$3:$B$14,$G7,sales_data!$E$3:$E$14,K$4) -> 0
A8: Февраль | B8: Периферия | C8: =SUMIFS(sales_data!$I$3:$I$14,sales_data!$B$3:$B$14,$A8,sales_data!$E$3:$E$14,$B8) -> 0 | D8: =SUMIFS(sales_data!$G$3:$G$14,sales_data!$B$3:$B$14,$A8,sales_data!$E$3:$E$14,$B8) -> 0 | E8: =COUNTIFS(sales_data!$B$3:$B$14,$A8,sales_data!$E$3:$E$14,$B8) -> 0 | G8: Апрель | H8: =SUMIFS(sales_data!$I$3:$I$14,sales_data!$B$3:$B$14,$G8,sales_data!$E$3:$E$14,H$4) -> 0 | I8: =SUMIFS(sales_data!$I$3:$I$14,sales_data!$B$3:$B$14,$G8,sales_data!$E$3:$E$14,I$4) -> 0 | J8: =SUMIFS(sales_data!$I$3:$I$14,sales_data!$B$3:$B$14,$G8,sales_data!$E$3:$E$14,J$4) -> 0 | K8: =SUMIFS(sales_data!$I$3:$I$14,sales_data!$B$3:$B$14,$G8,sales_data!$E$3:$E$14,K$4) -> 0
A9: Март | B9: Мониторы | C9: =SUMIFS(sales_data!$I$3:$I$14,sales_data!$B$3:$B$14,$A9,sales_data!$E$3:$E$14,$B9) -> 0 | D9: =SUMIFS(sales_data!$G$3:$G$14,sales_data!$B$3:$B$14,$A9,sales_data!$E$3:$E$14,$B9) -> 0 | E9: =COUNTIFS(sales_data!$B$3:$B$14,$A9,sales_data!$E$3:$E$14,$B9) -> 0
A10: Март | B10: Ноутбуки | C10: =SUMIFS(sales_data!$I$3:$I$14,sales_data!$B$3:$B$14,$A10,sales_data!$E$3:$E$14,$B10) -> 0 | D10: =SUMIFS(sales_data!$G$3:$G$14,sales_data!$B$3:$B$14,$A10,sales_data!$E$3:$E$14,$B10) -> 0 | E10: =COUNTIFS(sales_data!$B$3:$B$14,$A10,sales_data!$E$3:$E$14,$B10) -> 0
A11: Март | B11: Периферия | C11: =SUMIFS(sales_data!$I$3:$I$14,sales_data!$B$3:$B$14,$A11,sales_data!$E$3:$E$14,$B11) -> 0 | D11: =SUMIFS(sales_data!$G$3:$G$14,sales_data!$B$3:$B$14,$A11,sales_data!$E$3:$E$14,$B11) -> 0 | E11: =COUNTIFS(sales_data!$B$3:$B$14,$A11,sales_data!$E$3:$E$14,$B11) -> 0
A12: Март | B12: Принтеры | C12: =SUMIFS(sales_data!$I$3:$I$14,sales_data!$B$3:$B$14,$A12,sales_data!$E$3:$E$14,$B12) -> 0 | D12: =SUMIFS(sales_data!$G$3:$G$14,sales_data!$B$3:$B$14,$A12,sales_data!$E$3:$E$14,$B12) -> 0 | E12: =COUNTIFS(sales_data!$B$3:$B$14,$A12,sales_data!$E$3:$E$14,$B12) -> 0
A13: Апрель | B13: Ноутбуки | C13: =SUMIFS(sales_data!$I$3:$I$14,sales_data!$B$3:$B$14,$A13,sales_data!$E$3:$E$14,$B13) -> 0 | D13: =SUMIFS(sales_data!$G$3:$G$14,sales_data!$B$3:$B$14,$A13,sales_data!$E$3:$E$14,$B13) -> 0 | E13: =COUNTIFS(sales_data!$B$3:$B$14,$A13,sales_data!$E$3:$E$14,$B13) -> 0
A14: Апрель | B14: Периферия | C14: =SUMIFS(sales_data!$I$3:$I$14,sales_data!$B$3:$B$14,$A14,sales_data!$E$3:$E$14,$B14) -> 0 | D14: =SUMIFS(sales_data!$G$3:$G$14,sales_data!$B$3:$B$14,$A14,sales_data!$E$3:$E$14,$B14) -> 0 | E14: =COUNTIFS(sales_data!$B$3:$B$14,$A14,sales_data!$E$3:$E$14,$B14) -> 0

Sheet 4_Сортировка
A1: Шаг 4. Сортируем итоговые значения и ищем лидера
A3: manager | B3: total_revenue | C3: orders | D3: rank_by_revenue | F3: rank | G3: manager | H3: total_revenue
A4: ='2_Группировка_1'!A4 -> Анна | B4: ='2_Группировка_1'!B4 -> 0 | C4: ='2_Группировка_1'!C4 -> 0 | D4: =_xludf.RANK.EQ(B4,$B$4:$B$6,0) -> #NAME? | F4: 1 | G4: =INDEX($A$4:$A$6,MATCH(F4,$D$4:$D$6,0)) -> #N/A | H4: =INDEX($B$4:$B$6,MATCH(F4,$D$4:$D$6,0)) -> #N/A
A5: ='2_Группировка_1'!A5 -> Борис | B5: ='2_Группировка_1'!B5 -> 0 | C5: ='2_Группировка_1'!C5 -> 0 | D5: =_xludf.RANK.EQ(B5,$B$4:$B$6,0) -> #NAME? | F5: 2 | G5: =INDEX($A$4:$A$6,MATCH(F5,$D$4:$D$6,0)) -> #N/A | H5: =INDEX($B$4:$B$6,MATCH(F5,$D$4:$D$6,0)) -> #N/A
A6: ='2_Группировка_1'!A6 -> Светлана | B6: ='2_Группировка_1'!B6 -> 0 | C6: ='2_Группировка_1'!C6 -> 0 | D6: =_xludf.RANK.EQ(B6,$B$4:$B$6,0) -> #NAME? | F6: 3 | G6: =INDEX($A$4:$A$6,MATCH(F6,$D$4:$D$6,0)) -> #N/A | H6: =INDEX($B$4:$B$6,MATCH(F6,$D$4:$D$6,0)) -> #N/A
F8: Лидер по выручке | G8: =G4 -> #N/A | H8: =H4 -> #N/A

Sheet 5_Мини_сводная
A1: Шаг 5. Мини-сводная таблица revenue по manager и category
A3: manager | B3: Ноутбуки | C3: Мониторы | D3: Периферия | E3: Принтеры | F3: Итого
A4: Анна | B4: =SUMIFS(sales_data!$I$3:$I$14,sales_data!$C$3:$C$14,$A4,sales_data!$E$3:$E$14,B$3) -> 0 | C4: =SUMIFS(sales_data!$I$3:$I$14,sales_data!$C$3:$C$14,$A4,sales_data!$E$3:$E$14,C$3) -> 0 | D4: =SUMIFS(sales_data!$I$3:$I$14,sales_data!$C$3:$C$14,$A4,sales_data!$E$3:$E$14,D$3) -> 0 | E4: =SUMIFS(sales_data!$I$3:$I$14,sales_data!$C$3:$C$14,$A4,sales_data!$E$3:$E$14,E$3) -> 0 | F4: =SUM(B4:E4) -> 0
A5: Борис | B5: =SUMIFS(sales_data!$I$3:$I$14,sales_data!$C$3:$C$14,$A5,sales_data!$E$3:$E$14,B$3) -> 0 | C5: =SUMIFS(sales_data!$I$3:$I$14,sales_data!$C$3:$C$14,$A5,sales_data!$E$3:$E$14,C$3) -> 0 | D5: =SUMIFS(sales_data!$I$3:$I$14,sales_data!$C$3:$C$14,$A5,sales_data!$E$3:$E$14,D$3) -> 0 | E5: =SUMIFS(sales_data!$I$3:$I$14,sales_data!$C$3:$C$14,$A5,sales_data!$E$3:$E$14,E$3) -> 0 | F5: =SUM(B5:E5) -> 0
A6: Светлана | B6: =SUMIFS(sales_data!$I$3:$I$14,sales_data!$C$3:$C$14,$A6,sales_data!$E$3:$E$14,B$3) -> 0 | C6: =SUMIFS(sales_data!$I$3:$I$14,sales_data!$C$3:$C$14,$A6,sales_data!$E$3:$E$14,C$3) -> 0 | D6: =SUMIFS(sales_data!$I$3:$I$14,sales_data!$C$3:$C$14,$A6,sales_data!$E$3:$E$14,D$3) -> 0 | E6: =SUMIFS(sales_data!$I$3:$I$14,sales_data!$C$3:$C$14,$A6,sales_data!$E$3:$E$14,E$3) -> 0 | F6: =SUM(B6:E6) -> 0
A7: Итого | B7: =SUM(B4:B6) -> 0 | C7: =SUM(C4:C6) -> 0 | D7: =SUM(D4:D6) -> 0 | E7: =SUM(E4:E6) -> 0 | F7: =SUM(F4:F6) -> 0
A9: Лучшая категория | B9: =INDEX(B$3:E$3,MATCH(MAX(B7:E7),B7:E7,0)) -> Ноутбуки | C9: Выручка | D9: =MAX(B7:E7) -> 0

Sheet 6_Тест
A1: Тест по занятию 9
A3: Вопрос | B3: Правильный ответ | C3: Подсказка
A4: Сколько заказов в исходной таблице? | B4: =COUNTA(sales_data!A3:A14) -> 12 | C4: Смотрите sheet sales_data или df.shape[0].
A5: Какая общая выручка по всем заказам? | B5: =SUM(sales_data!I3:I14) -> 8354155.8 | C5: Это сумма revenue.
A6: Кто лидер по выручке среди менеджеров? | B6: ='4_Сортировка'!G8 -> #N/A | C6: Используйте groupby по manager и sort_values().
A7: Какая выручка у категории 'Ноутбуки'? | B7: ='5_Мини_сводная'!B7 -> 0 | C7: Посмотрите итоги по столбцам в мини-сводной.
A8: Сколько заказов у Анны? | B8: =COUNTIF(sales_data!C3:C14,"Анна") -> 0 | C8: Аналог groupby().count().
